[
    {
        "run_key": "fewshot_qwq-32b_guv-waisenrente",
        "valid_turtle": 1,
        "valid_shacl": 0,
        "graph_edit_distance": 0.5705882352941176,
        "ged_timeout": 1,
        "gbert_precision": 0.985,
        "gbert_recall": 0.6594,
        "gbert_f1": 0.79,
        "triple_accuracy": 0.6329,
        "triple_precision": 0.4359,
        "triple_recall": 0.2833,
        "triple_f1": 0.3434,
        "validation_accuracy": 0,
        "validation_precision": 0,
        "validation_recall": 0,
        "validation_f1": 0
    },
    {
        "run_key": "fewshot_qwq-32b_einstiegsgeld",
        "valid_turtle": 0,
        "valid_shacl": 0,
        "graph_edit_distance": 1,
        "gbert_precision": 0,
        "gbert_recall": 0,
        "gbert_f1": 0,
        "triple_accuracy": 0,
        "triple_precision": 0,
        "triple_recall": 0,
        "triple_f1": 0,
        "validation_accuracy": 0,
        "validation_precision": 0,
        "validation_recall": 0,
        "validation_f1": 0
    },
    {
        "run_key": "fewshot_qwq-32b_guv-rentenabfindung",
        "valid_turtle": 1,
        "valid_shacl": 0,
        "graph_edit_distance": 0.4594594594594595,
        "ged_timeout": 1,
        "gbert_precision": 0.8519,
        "gbert_recall": 0.9781,
        "gbert_f1": 0.9106,
        "triple_accuracy": 0.4839,
        "triple_precision": 0.44,
        "triple_recall": 0.5,
        "triple_f1": 0.4681,
        "validation_accuracy": 0,
        "validation_precision": 0,
        "validation_recall": 0,
        "validation_f1": 0
    },
    {
        "run_key": "fewshot_qwq-32b_guv-uebergangsgeld",
        "valid_turtle": 1,
        "valid_shacl": 0,
        "graph_edit_distance": 0.4766355140186916,
        "ged_timeout": 1,
        "gbert_precision": 0.9772,
        "gbert_recall": 0.6718,
        "gbert_f1": 0.7962,
        "triple_accuracy": 0.4091,
        "triple_precision": 0.3684,
        "triple_recall": 0.2593,
        "triple_f1": 0.3043,
        "validation_accuracy": 0,
        "validation_precision": 0,
        "validation_recall": 0,
        "validation_f1": 0
    },
    {
        "run_key": "fewshot_qwq-32b_uebergangsgeld-behinderung",
        "valid_turtle": 0,
        "valid_shacl": 0,
        "graph_edit_distance": 1,
        "gbert_precision": 0,
        "gbert_recall": 0,
        "gbert_f1": 0,
        "triple_accuracy": 0,
        "triple_precision": 0,
        "triple_recall": 0,
        "triple_f1": 0,
        "validation_accuracy": 0,
        "validation_precision": 0,
        "validation_recall": 0,
        "validation_f1": 0
    },
    {
        "run_key": "fewshot_qwq-32b_kinderzuschlag",
        "valid_turtle": 1,
        "valid_shacl": null,
        "graph_edit_distance": 0.45652173913043476,
        "ged_timeout": 1,
        "gbert_precision": 0.9948,
        "gbert_recall": 0.9099,
        "gbert_f1": 0.9504,
        "triple_accuracy": 0.92,
        "triple_precision": 0.88,
        "triple_recall": 0.898,
        "triple_f1": 0.8889,
        "validation_accuracy": 0,
        "validation_precision": 0,
        "validation_recall": 0,
        "validation_f1": 0
    },
    {
        "run_key": "fewshot_qwq-32b_buergergeld",
        "valid_turtle": 0,
        "valid_shacl": 0,
        "graph_edit_distance": 1,
        "gbert_precision": 0,
        "gbert_recall": 0,
        "gbert_f1": 0,
        "triple_accuracy": 0,
        "triple_precision": 0,
        "triple_recall": 0,
        "triple_f1": 0,
        "validation_accuracy": 0,
        "validation_precision": 0,
        "validation_recall": 0,
        "validation_f1": 0
    },
    {
        "run_key": "fewshot_qwq-32b_aktivierung-und-eingliederung",
        "valid_turtle": 1,
        "valid_shacl": null,
        "graph_edit_distance": 0.4098360655737705,
        "ged_timeout": 1,
        "gbert_precision": 0.539,
        "gbert_recall": 0.98,
        "gbert_f1": 0.6955,
        "triple_accuracy": 0.45,
        "triple_precision": 0.3889,
        "triple_recall": 0.6364,
        "triple_f1": 0.4828,
        "validation_accuracy": 0,
        "validation_precision": 0,
        "validation_recall": 0,
        "validation_f1": 0
    },
    {
        "run_key": "fewshot_qwq-32b_guv-verletztengeld",
        "valid_turtle": 1,
        "valid_shacl": 1,
        "graph_edit_distance": 0.40625,
        "ged_timeout": 1,
        "gbert_precision": 0.9658,
        "gbert_recall": 0.9951,
        "gbert_f1": 0.9802,
        "triple_accuracy": 0.8235,
        "triple_precision": 0.7778,
        "triple_recall": 0.8077,
        "triple_f1": 0.7925,
        "validation_precision": 1.0,
        "validation_recall": 1.0,
        "validation_accuracy": 1.0,
        "validation_f1": 1.0
    },
    {
        "run_key": "fewshot_qwq-32b_bildung-und-teilhabe",
        "valid_turtle": 0,
        "valid_shacl": 0,
        "graph_edit_distance": 1,
        "gbert_precision": 0,
        "gbert_recall": 0,
        "gbert_f1": 0,
        "triple_accuracy": 0,
        "triple_precision": 0,
        "triple_recall": 0,
        "triple_f1": 0,
        "validation_accuracy": 0,
        "validation_precision": 0,
        "validation_recall": 0,
        "validation_f1": 0
    },
    {
        "run_key": "fewshot_qwq-32b_guv-rente",
        "valid_turtle": 0,
        "valid_shacl": 0,
        "graph_edit_distance": 1,
        "gbert_precision": 0,
        "gbert_recall": 0,
        "gbert_f1": 0,
        "triple_accuracy": 0,
        "triple_precision": 0,
        "triple_recall": 0,
        "triple_f1": 0,
        "validation_accuracy": 0,
        "validation_precision": 0,
        "validation_recall": 0,
        "validation_f1": 0
    },
    {
        "run_key": "fewshot_qwq-32b_guv-witwenrente",
        "valid_turtle": 1,
        "valid_shacl": 1,
        "graph_edit_distance": 0.43209876543209874,
        "ged_timeout": 1,
        "gbert_precision": 1.0,
        "gbert_recall": 1.0,
        "gbert_f1": 1.0,
        "triple_accuracy": 1.0,
        "triple_precision": 1.0,
        "triple_recall": 1.0,
        "triple_f1": 1.0,
        "validation_precision": 1.0,
        "validation_recall": 1.0,
        "validation_accuracy": 1.0,
        "validation_f1": 1.0
    },
    {
        "run_key": "fewshot_qwq-32b_berufsausbildungsbeihilfe",
        "valid_turtle": 0,
        "valid_shacl": 0,
        "graph_edit_distance": 1,
        "gbert_precision": 0,
        "gbert_recall": 0,
        "gbert_f1": 0,
        "triple_accuracy": 0,
        "triple_precision": 0,
        "triple_recall": 0,
        "triple_f1": 0,
        "validation_accuracy": 0,
        "validation_precision": 0,
        "validation_recall": 0,
        "validation_f1": 0
    },
    {
        "run_key": "fewshot_qwq-32b_ausbildungsgeld",
        "valid_turtle": 1,
        "valid_shacl": 0,
        "graph_edit_distance": 0.48148148148148145,
        "ged_timeout": 1,
        "gbert_precision": 0.8192,
        "gbert_recall": 0.9831,
        "gbert_f1": 0.8937,
        "triple_accuracy": 0.5333,
        "triple_precision": 0.44,
        "triple_recall": 0.5789,
        "triple_f1": 0.5,
        "validation_accuracy": 0,
        "validation_precision": 0,
        "validation_recall": 0,
        "validation_f1": 0
    },
    {
        "run_key": "fewshot_qwq-32b_arbeitslosengeld",
        "valid_turtle": 0,
        "valid_shacl": 0,
        "graph_edit_distance": 1,
        "gbert_precision": 0,
        "gbert_recall": 0,
        "gbert_f1": 0,
        "triple_accuracy": 0,
        "triple_precision": 0,
        "triple_recall": 0,
        "triple_f1": 0,
        "validation_accuracy": 0,
        "validation_precision": 0,
        "validation_recall": 0,
        "validation_f1": 0
    },
    {
        "run_key": "fewshot_qwq-32b_grundausbildung",
        "valid_turtle": 1,
        "valid_shacl": 0,
        "graph_edit_distance": 0.4426229508196721,
        "ged_timeout": 1,
        "gbert_precision": 0.9336,
        "gbert_recall": 0.9874,
        "gbert_f1": 0.9597,
        "triple_accuracy": 0.8727,
        "triple_precision": 0.8438,
        "triple_recall": 0.871,
        "triple_f1": 0.8571,
        "validation_accuracy": 0,
        "validation_precision": 0,
        "validation_recall": 0,
        "validation_f1": 0
    },
    {
        "run_key": "fewshot_qwq-32b_insolvenzgeld",
        "valid_turtle": 1,
        "valid_shacl": 1,
        "graph_edit_distance": 0.6084905660377359,
        "ged_timeout": 1,
        "gbert_precision": 0.7599,
        "gbert_recall": 0.9885,
        "gbert_f1": 0.8593,
        "triple_accuracy": 0.9116,
        "triple_precision": 0.76,
        "triple_recall": 0.6552,
        "triple_f1": 0.7037,
        "validation_precision": 0.0,
        "validation_recall": 0.0,
        "validation_accuracy": 0.9841,
        "validation_f1": 0.0
    },
    {
        "run_key": "fewshot_qwq-32b_grundsicherung",
        "valid_turtle": 0,
        "valid_shacl": 0,
        "graph_edit_distance": 1,
        "gbert_precision": 0,
        "gbert_recall": 0,
        "gbert_f1": 0,
        "triple_accuracy": 0,
        "triple_precision": 0,
        "triple_recall": 0,
        "triple_f1": 0,
        "validation_accuracy": 0,
        "validation_precision": 0,
        "validation_recall": 0,
        "validation_f1": 0
    },
    {
        "run_key": "fewshot_qwq-32b_krankengeld-begleitperson",
        "valid_turtle": 0,
        "valid_shacl": 0,
        "graph_edit_distance": 1,
        "gbert_precision": 0,
        "gbert_recall": 0,
        "gbert_f1": 0,
        "triple_accuracy": 0,
        "triple_precision": 0,
        "triple_recall": 0,
        "triple_f1": 0,
        "validation_accuracy": 0,
        "validation_precision": 0,
        "validation_recall": 0,
        "validation_f1": 0
    }
]